kmup/__init__.py
kmup/cli.py
kmup/main.py
kmup/kmpkg/__init__.py
kmup/kmpkg/commands.py
kmup-1.1.5.dist-info/LICENSE
kmup-1.1.5.dist-info/METADATA
kmup-1.1.5.dist-info/WHEEL
kmup-1.1.5.dist-info/entry_points.txt
kmup-1.1.5.dist-info/top_level.txt
kmup-1.1.5.dist-info/RECORD
